pyrex.py
PyRexMacro-0.1.dist-info/LICENSE
PyRexMacro-0.1.dist-info/METADATA
PyRexMacro-0.1.dist-info/WHEEL
PyRexMacro-0.1.dist-info/top_level.txt
PyRexMacro-0.1.dist-info/RECORD
